rcdpeaks_functions/__init__.py
rcdpeaks_functions/__main__.py
rcdpeaks_functions/dpfuncs.py
rcdpeaks-0.0.1.dist-info/LICENCE
rcdpeaks-0.0.1.dist-info/METADATA
rcdpeaks-0.0.1.dist-info/WHEEL
rcdpeaks-0.0.1.dist-info/entry_points.txt
rcdpeaks-0.0.1.dist-info/top_level.txt
rcdpeaks-0.0.1.dist-info/RECORD
