Metadata-Version: 2.1
Name: rcdpeaks
Version: 0.0.1
Summary: Memory-Efficient Density Peaks Clustering for Long Molecular Dynamics
Home-page: https://github.com/LQCT/RCDPeaks.git
Author: Daniel Platero-Rochart
Author-email: daniel.platero@fq.uh.cu
License: UNKNOWN
Platform: UNKNOWN
Classifier: Programming Language :: Python :: 3
Classifier: Programming Language :: Python :: 3.8
Requires-Dist: numpy (>=1.17.2)
Requires-Dist: pandas (>=0.25.1)
Requires-Dist: matplotlib (>=3.1.0)
Requires-Dist: mdtraj (>=1.9.4)
Requires-Dist: networkx (>=2.3)
